wrpy/__init__.py
wrpy/core.py
wrpy/services.py
wrpy-0.1.3.dist-info/METADATA
wrpy-0.1.3.dist-info/WHEEL
wrpy-0.1.3.dist-info/licenses/LICENSE
wrpy-0.1.3.dist-info/RECORD
