Metadata-Version: 2.4
Name: wrpy
Version: 0.1.3
Summary: Get translations from WordReference
Author-email: Sergio Delgado Quintero <sdelquin@gmail.com>
License-File: LICENSE
Requires-Python: >=3.8
Requires-Dist: beautifulsoup4>=4.13.3
Requires-Dist: requests>=2.32.3
Requires-Dist: user-agent>=0.1.10
